Chatbot/__init__.py
Chatbot/main_module.py
cancer_chatbot/Final_Stacked_Data_without_Duplicates.csv
cancer_chatbot/__init__.py
cancer_chatbot/main.py
main/__init__.py
main/main.py
cancer_chatbot-0.1.8.dist-info/METADATA
cancer_chatbot-0.1.8.dist-info/WHEEL
cancer_chatbot-0.1.8.dist-info/entry_points.txt
cancer_chatbot-0.1.8.dist-info/top_level.txt
cancer_chatbot-0.1.8.dist-info/RECORD
