Metadata-Version: 2.1
Name: cancer_chatbot
Version: 0.1.8
Summary: This is a chatbot created to answer all your questions related to cancer and cancer research from various journal articles such as PubMed, Biorxiv.
Home-page: https://github.com/Dorcatz123/cancer_chatbot.git
Author: Akshay P R, Kiran K T
Author-email: akshaypr314159@gmail.com
Classifier: Programming Language :: Python :: 3
Classifier: License :: OSI Approved :: GNU General Public License v3 (GPLv3)
Classifier: Operating System :: OS Independent
Requires-Python: >=3.9
Requires-Dist: numpy
Requires-Dist: pandas
Requires-Dist: langchain
Requires-Dist: langchain-openai
Requires-Dist: langchain-community
Requires-Dist: faiss-cpu
Requires-Dist: langchain-core
